create_order.py
module_update.py
registrar_test.py
registration.py
test2.py
test_3.py
test_4.py
test_5.py
workflow_example.py
biosero/__init__.py
biosero/datamodels/__init__.py
biosero/datamodels/view_model.py
biosero/datamodels/adapter/__init__.py
biosero/datamodels/adapter/decorators.py
biosero/datamodels/adapter/generate_library.py
biosero/datamodels/adapter/helpers.py
biosero/datamodels/adapter/order_processer.py
biosero/datamodels/adapter/template_categories.py
biosero/datamodels/adapter/template_icons.py
biosero/datamodels/adapter/template_registrar.py
biosero/datamodels/clients/__init__.py
biosero/datamodels/clients/iorder_client.py
biosero/datamodels/events/__init__.py
biosero/datamodels/events/event.py
biosero/datamodels/events/event_message.py
biosero/datamodels/events/event_search_parameters.py
biosero/datamodels/events/eventcontext.py
biosero/datamodels/events/liquid_transfer_event.py
biosero/datamodels/events/location_changed_event.py
biosero/datamodels/events/module_status_update_event.py
biosero/datamodels/extensions/__init__.py
biosero/datamodels/extensions/exception_extensions.py
biosero/datamodels/extensions/object_extesion.py
biosero/datamodels/extensions/string_extensions.py
biosero/datamodels/helpers/__init__.py
biosero/datamodels/helpers/enum_helper.py
biosero/datamodels/helpers/http_client_helper.py
biosero/datamodels/helpers/string_helper.py
biosero/datamodels/helpers/unique_identifier_provider.py
biosero/datamodels/helpers/well_helper.py
biosero/datamodels/measurement/__init__.py
biosero/datamodels/measurement/concentration.py
biosero/datamodels/measurement/coordinates.py
biosero/datamodels/measurement/evaluator.py
biosero/datamodels/measurement/inventorylevel.py
biosero/datamodels/measurement/inventorythreshold.py
biosero/datamodels/measurement/location.py
biosero/datamodels/measurement/materialstate.py
biosero/datamodels/measurement/temperature.py
biosero/datamodels/measurement/volume.py
biosero/datamodels/measurement/weight.py
biosero_data_models-0.2.0.dist-info/licenses/LICENSE
biosero_data_models-0.2.0.dist-info/METADATA
biosero_data_models-0.2.0.dist-info/WHEEL
biosero_data_models-0.2.0.dist-info/top_level.txt
biosero_data_models-0.2.0.dist-info/RECORD
