Metadata-Version: 2.4
Name: biosero-data-models
Version: 0.2.0
Summary: A python library with client and contract code to work with the Data Services API
Author-email: Pete Werner <peterwerner@biosero.com>
License: Apache-2.0
Project-URL: Homepage, https://github.com/biosero/data-models-python
License-File: LICENSE
Requires-Dist: anyio==4.4.0
Requires-Dist: aiohttp==3.9.5
Requires-Dist: certifi==2024.6.2
Requires-Dist: charset-normalizer==3.3.2
Requires-Dist: h11==0.14.0
Requires-Dist: httpcore==1.0.5
Requires-Dist: httpx==0.27.0
Requires-Dist: idna==3.7
Requires-Dist: jsonpickle==4.0.5
Requires-Dist: requests==2.32.3
Requires-Dist: sniffio==1.3.1
Requires-Dist: rich==13.7.1
Dynamic: license-file
